jitools/__init__.py
jitools/constants.py
jitools/pitch.py
jitools/pitch_collection.py
jitools/prime_list.py
jitools/utilities_general.py
jitools/utilities_music.py
jitools/resources/enharmonic_lookup_table.csv
jitools-0.3.dist-info/LICENSE.txt
jitools-0.3.dist-info/METADATA
jitools-0.3.dist-info/WHEEL
jitools-0.3.dist-info/top_level.txt
jitools-0.3.dist-info/RECORD
