Metadata-Version: 2.1
Name: jitools
Version: 0.3
Summary: a Python-based set of utilities for just intonation (JI) pitch and pitch collection research and analysis
Home-page: https://github.com/moab-bot/jitools
Author: M.O. Abbott
Author-email: moab_bot@protonmail.com
License: GNU GPLv3
Download-URL: https://github.com/moab-bot/jitools/archive/v_03.tar.gz
Platform: UNKNOWN
Classifier: Programming Language :: Python :: 3
Classifier: License :: OSI Approved :: GNU General Public License v3 or later (GPLv3+)
Classifier: Operating System :: OS Independent
Requires-Python: >=3.9.4
